iron_gql/__init__.py
iron_gql/generator.py
iron_gql/parser.py
iron_gql/py.typed
iron_gql/runtime.py
iron_gql/util.py
iron_gql-0.2.5.dist-info/licenses/LICENSE
iron_gql-0.2.5.dist-info/WHEEL
iron_gql-0.2.5.dist-info/METADATA
iron_gql-0.2.5.dist-info/RECORD
