Metadata-Version: 2.4
Name: iron-gql
Version: 0.2.5
Summary: iron_gql generates typed async GraphQL clients and runtime helpers from schemas for Python services
Keywords: graphql,gql,client,httpx,pydantic,codegen,async
Author: Ilia Ablamonov
Author-email: Ilia Ablamonov <ilia@flamefork.ru>
License-Expression: MIT
License-File: LICENSE
Classifier: Development Status :: 3 - Alpha
Classifier: Intended Audience :: Developers
Classifier: Topic :: Software Development :: Libraries
Classifier: Programming Language :: Python :: 3
Classifier: Programming Language :: Python :: 3.13
Requires-Dist: gql>=4.0.0,<5
Requires-Dist: httpx>=0.28.1,<1
Requires-Dist: pydantic>=2.12.3,<3
Requires-Python: >=3.13
Project-URL: Homepage, https://github.com/Flamefork/iron_gql
Project-URL: Repository, https://github.com/Flamefork/iron_gql.git
Project-URL: Issues, https://github.com/Flamefork/iron_gql/issues
